{
"autoplayBgm":false,"autoplayBgs":false,"battleback1Name":"","battleback2Name":"","bgm":{"name":"","pan":0,"pitch":100,"volume":90},"bgs":{"name":"","pan":0,"pitch":100,"volume":90},"disableDashing":false,"displayName":"","encounterList":[],"encounterStep":30,"height":8,"note":"","parallaxLoopX":false,"parallaxLoopY":false,"parallaxName":"","parallaxShow":true,"parallaxSx":0,"parallaxSy":0,"scrollType":0,"specifyBattleback":false,"tilesetId":7,"width":9,
"data":[1536,1546,1546,1546,1546,1546,1546,1569,1569,1545,1545,1554,1554,1570,1554,1562,1569,1569,1569,1553,1570,1570,1570,1570,1570,1569,1569,1569,1570,1570,1570,1570,1570,1570,1569,1569,1569,1570,1570,1570,1570,1570,1569,1569,1569,1569,1570,1570,1570,1570,1570,1570,1569,1569,1570,1570,1570,1570,1570,1570,1570,1569,1569,1569,1569,1569,1569,1569,1569,1569,1569,1569,0,0,0,0,0,0,0,0,0,0,0,0,0,0,0,0,0,0,0,0,0,0,0,0,0,0,0,0,0,0,0,0,0,0,0,0,0,0,0,0,0,0,0,0,0,0,0,0,0,0,0,0,0,0,0,0,0,0,0,0,0,0,0,0,0,0,0,0,0,0,0,0,0,0,0,0,0,0,0,0,0,0,0,1,1,1,1,1,0,0,0,0,1,1,1,1,1,0,0,0,1,1,1,1,1,1,0,0,0,1,1,1,1,1,1,0,0,0,0,34,1,1,1,34,0,0,0,0,34,34,34,34,34,0,0,0,0,0,0,0,0,0,0,0,1,1,1,1,1,1,1,1,1,1,1,8,9,34,11,12,1,1,1,1,16,17,34,19,20,1,1,1,13,24,34,34,34,28,1,1,1,13,34,34,34,34,33,1,1,1,1,32,34,25,34,36,1,1,1,1,40,41,42,43,44,1,1,1,1,1,1,1,1,1,1,1,0,0,0,0,0,0,0,0,0,0,0,0,0,0,0,0,0,0,0,0,0,0,0,0,0,0,0,0,0,0,0,0,0,0,0,0,0,0,0,0,0,0,0,0,0,0,0,0,0,0,0,0,0,0,0,0,0,0,0,0,0,0,0,0,0,0,0,0,0,0,0,0,0,0,0,0,0,0,0,0,0,0,0,0,0,0,0,0,0,0,0,0,0,0,0,0,0,0,0,0,0,0,0,0,0,0,0,0,0,0,0,0,0,0,0,0,0,0,0,0,0,0,0,0,0,0,0,0,0,0,0,0,0,0,0,0,0,0,0,0,0,0,0,0],
"events":[
null,
{"id":1,"name":"EV001","note":"","pages":[{"conditions":{"actorId":1,"actorValid":false,"itemId":1,"itemValid":false,"selfSwitchCh":"A","selfSwitchValid":false,"switch1Id":1,"switch1Valid":false,"switch2Id":1,"switch2Valid":false,"variableId":1,"variableValid":false,"variableValue":0},"directionFix":false,"image":{"characterIndex":0,"characterName":"","direction":2,"pattern":0,"tileId":0},"list":[{"code":201,"indent":0,"parameters":[0,2,7,10,0,0]},{"code":0,"indent":0,"parameters":[]}],"moveFrequency":3,"moveRoute":{"list":[{"code":0,"parameters":[]}],"repeat":true,"skippable":false,"wait":false},"moveSpeed":3,"moveType":0,"priorityType":0,"stepAnime":false,"through":false,"trigger":0,"walkAnime":true}],"x":4,"y":1},
{"id":2,"name":"slime slayer","note":"","pages":[{"conditions":{"actorId":1,"actorValid":false,"itemId":1,"itemValid":false,"selfSwitchCh":"A","selfSwitchValid":false,"switch1Id":1,"switch1Valid":false,"switch2Id":1,"switch2Valid":false,"variableId":1,"variableValid":false,"variableValue":0},"directionFix":false,"image":{"tileId":0,"characterName":"Slime_slayer","direction":2,"pattern":1,"characterIndex":0},"list":[{"code":101,"indent":0,"parameters":["Slime_slayer",0,0,2]},{"code":401,"indent":0,"parameters":["I just killed 1,000,000 slimes."]},{"code":101,"indent":0,"parameters":["Slime_slayer",0,0,2]},{"code":401,"indent":0,"parameters":["The slime king is going to spawn any moment."]},{"code":101,"indent":0,"parameters":["Slime_slayer",0,0,2]},{"code":401,"indent":0,"parameters":["Would you help me defeat it?"]},{"code":102,"indent":0,"parameters":[["I'll help!","Nah."],1,0,2,0]},{"code":402,"indent":0,"parameters":[0,"I'll help!"]},{"code":121,"indent":1,"parameters":[11,11,0]},{"code":0,"indent":1,"parameters":[]},{"code":402,"indent":0,"parameters":[1,"Nah."]},{"code":117,"indent":1,"parameters":[3]},{"code":111,"indent":1,"parameters":[0,3,0]},{"code":121,"indent":2,"parameters":[3,3,1]},{"code":123,"indent":2,"parameters":["B",0]},{"code":0,"indent":2,"parameters":[]},{"code":412,"indent":1,"parameters":[]},{"code":0,"indent":1,"parameters":[]},{"code":404,"indent":0,"parameters":[]},{"code":0,"indent":0,"parameters":[]}],"moveFrequency":3,"moveRoute":{"list":[{"code":0,"parameters":[]}],"repeat":true,"skippable":false,"wait":false},"moveSpeed":3,"moveType":0,"priorityType":1,"stepAnime":false,"through":false,"trigger":0,"walkAnime":true},{"conditions":{"actorId":1,"actorValid":false,"itemId":1,"itemValid":false,"selfSwitchCh":"B","selfSwitchValid":true,"switch1Id":1,"switch1Valid":false,"switch2Id":1,"switch2Valid":false,"variableId":1,"variableValid":false,"variableValue":0},"directionFix":true,"image":{"tileId":0,"characterName":"Slime_slayer","direction":2,"pattern":1,"characterIndex":4},"list":[{"code":0,"indent":0,"parameters":[]}],"moveFrequency":3,"moveRoute":{"list":[{"code":0,"parameters":[]}],"repeat":true,"skippable":false,"wait":false},"moveSpeed":3,"moveType":0,"priorityType":0,"stepAnime":false,"through":false,"trigger":0,"walkAnime":true}],"x":4,"y":4},
{"id":3,"name":"slime king","note":"","pages":[{"conditions":{"actorId":1,"actorValid":false,"itemId":1,"itemValid":false,"selfSwitchCh":"A","selfSwitchValid":false,"switch1Id":11,"switch1Valid":true,"switch2Id":1,"switch2Valid":false,"variableId":1,"variableValid":false,"variableValue":0},"directionFix":false,"image":{"tileId":0,"characterName":"$SlimeKing","direction":4,"pattern":1,"characterIndex":0},"list":[{"code":221,"indent":0,"parameters":[]},{"code":201,"indent":0,"parameters":[0,7,4,3,0,0]},{"code":222,"indent":0,"parameters":[]},{"code":205,"indent":0,"parameters":[-1,{"list":[{"code":18,"indent":null},{"code":0}],"repeat":false,"skippable":false,"wait":false}]},{"code":505,"indent":0,"parameters":[{"code":18,"indent":null}]},{"code":213,"indent":0,"parameters":[-1,1,false]},{"code":213,"indent":0,"parameters":[2,1,false]},{"code":205,"indent":0,"parameters":[2,{"list":[{"code":18,"indent":null},{"code":13,"indent":null},{"code":0}],"repeat":false,"skippable":false,"wait":true}]},{"code":505,"indent":0,"parameters":[{"code":18,"indent":null}]},{"code":505,"indent":0,"parameters":[{"code":13,"indent":null}]},{"code":101,"indent":0,"parameters":["Slime_slayer",2,0,2]},{"code":401,"indent":0,"parameters":["\\{Rahhhh!!!!"]},{"code":101,"indent":0,"parameters":["Slime_slayer",2,0,2]},{"code":401,"indent":0,"parameters":["\\{You have slained all my "]},{"code":401,"indent":0,"parameters":["children!!"]},{"code":101,"indent":0,"parameters":["Slime_slayer",2,0,2]},{"code":401,"indent":0,"parameters":["\\{It's my turn to end you now!!!!"]},{"code":250,"indent":0,"parameters":[{"name":"Earth1","volume":50,"pitch":100,"pan":0}]},{"code":205,"indent":0,"parameters":[0,{"list":[{"code":2,"indent":null},{"code":0}],"repeat":false,"skippable":false,"wait":true}]},{"code":505,"indent":0,"parameters":[{"code":2,"indent":null}]},{"code":250,"indent":0,"parameters":[{"name":"Earth1","volume":50,"pitch":100,"pan":0}]},{"code":101,"indent":0,"parameters":["Slime_slayer",1,0,2]},{"code":401,"indent":0,"parameters":["Let me help you!"]},{"code":212,"indent":0,"parameters":[0,6,true]},{"code":101,"indent":0,"parameters":["Slime_slayer",0,0,2]},{"code":401,"indent":0,"parameters":["Don't worry my frd."]},{"code":212,"indent":0,"parameters":[0,23,true]},{"code":224,"indent":0,"parameters":[[0,0,0,170],60,true]},{"code":224,"indent":0,"parameters":[[0,0,0,170],60,true]},{"code":224,"indent":0,"parameters":[[0,0,0,170],60,true]},{"code":101,"indent":0,"parameters":["Slime_slayer",2,0,2]},{"code":401,"indent":0,"parameters":["... ..."]},{"code":101,"indent":0,"parameters":["Slime_slayer",2,0,2]},{"code":401,"indent":0,"parameters":["You... Why did you help her?"]},{"code":101,"indent":0,"parameters":["Slime_slayer",2,0,2]},{"code":401,"indent":0,"parameters":["You are also slime, why did you betrayed "]},{"code":401,"indent":0,"parameters":["us?"]},{"code":101,"indent":0,"parameters":["Slime_slayer",1,0,2]},{"code":401,"indent":0,"parameters":["... ..."]},{"code":205,"indent":0,"parameters":[0,{"list":[{"code":41,"parameters":["",0],"indent":null},{"code":0}],"repeat":false,"skippable":false,"wait":true}]},{"code":505,"indent":0,"parameters":[{"code":41,"parameters":["",0],"indent":null}]},{"code":205,"indent":0,"parameters":[2,{"list":[{"code":3,"indent":null},{"code":19,"indent":null},{"code":0}],"repeat":false,"skippable":false,"wait":true}]},{"code":505,"indent":0,"parameters":[{"code":3,"indent":null}]},{"code":505,"indent":0,"parameters":[{"code":19,"indent":null}]},{"code":205,"indent":0,"parameters":[-1,{"list":[{"code":16,"indent":null},{"code":0}],"repeat":false,"skippable":false,"wait":true}]},{"code":505,"indent":0,"parameters":[{"code":16,"indent":null}]},{"code":101,"indent":0,"parameters":["Slime_slayer",0,0,2]},{"code":401,"indent":0,"parameters":["I know you are slime from the start."]},{"code":101,"indent":0,"parameters":["Slime_slayer",0,0,2]},{"code":401,"indent":0,"parameters":["How can I now know after killing that many "]},{"code":401,"indent":0,"parameters":["slime..."]},{"code":111,"indent":0,"parameters":[1,7,0,0,0]},{"code":101,"indent":1,"parameters":["Slime_slayer",0,0,2]},{"code":401,"indent":1,"parameters":["But I know you have a good heart."]},{"code":101,"indent":1,"parameters":["Slime_slayer",0,0,2]},{"code":401,"indent":1,"parameters":["You can live as a human."]},{"code":221,"indent":1,"parameters":[]},{"code":101,"indent":1,"parameters":["",0,1,1]},{"code":401,"indent":1,"parameters":["You kept this body and continued your life in "]},{"code":401,"indent":1,"parameters":["the human society."]},{"code":101,"indent":1,"parameters":["",0,1,1]},{"code":401,"indent":1,"parameters":["Killing other innocent creatures to gain exp.\\..\\.."]},{"code":230,"indent":1,"parameters":[30]},{"code":101,"indent":1,"parameters":["",0,0,2]},{"code":401,"indent":1,"parameters":["Thanks for playing."]},{"code":354,"indent":1,"parameters":[]},{"code":0,"indent":1,"parameters":[]},{"code":411,"indent":0,"parameters":[]},{"code":101,"indent":1,"parameters":["Slime_slayer",0,0,2]},{"code":401,"indent":1,"parameters":["But I also know that you killed someone "]},{"code":401,"indent":1,"parameters":["else."]},{"code":101,"indent":1,"parameters":["Slime_slayer",0,0,2]},{"code":401,"indent":1,"parameters":["Sorry that I can't let you live."]},{"code":101,"indent":1,"parameters":["Slime_slayer",0,0,2]},{"code":401,"indent":1,"parameters":["I will end you quick."]},{"code":221,"indent":1,"parameters":[]},{"code":250,"indent":1,"parameters":[{"name":"Attack3","volume":50,"pitch":100,"pan":0}]},{"code":101,"indent":1,"parameters":["",0,1,1]},{"code":401,"indent":1,"parameters":["You can't escape the fate of becoming exp.\\..\\.."]},{"code":101,"indent":1,"parameters":["",0,1,1]},{"code":401,"indent":1,"parameters":["You keep respawning and get killed."]},{"code":101,"indent":1,"parameters":["",0,1,1]},{"code":401,"indent":1,"parameters":["Again..\\| and again."]},{"code":230,"indent":1,"parameters":[30]},{"code":101,"indent":1,"parameters":["",0,0,2]},{"code":401,"indent":1,"parameters":["Thanks for playing."]},{"code":354,"indent":1,"parameters":[]},{"code":0,"indent":1,"parameters":[]},{"code":412,"indent":0,"parameters":[]},{"code":0,"indent":0,"parameters":[]}],"moveFrequency":3,"moveRoute":{"list":[{"code":0,"parameters":[]}],"repeat":true,"skippable":false,"wait":false},"moveSpeed":3,"moveType":0,"priorityType":2,"stepAnime":false,"through":true,"trigger":3,"walkAnime":true}],"x":6,"y":6}
]
}